{"job_id":"14213176-1154195478-2f7dae19-0a1b-4f21-8545-39a547c4de53","session_id":"c8009b8c-218d-4c24-a435-4b8f88c4ec22","created_at":"2026-02-10T09:24:07+00:00","completed_at":null,"status":"queued","problem_statement":"# Call skill execute-modernization-plan to Execute modernization plan\r\n\r\n## Using the below context\r\n\r\n- modernization-description: execute the upgrade plan\r\n- modernization-work-folder: .github\\modernization\\018-upgrade-to-lts\r\n","pull_request":{"number":6,"title":"[WIP] Execute modernization plan for upgrade","base_ref":"appmod/java-upgrade-20260210084029","head_ref":"copilot/execute-modernization-plan-yet-again"},"actor":{"id":14213176,"login":"yuwzho"},"repository":{"owner":"yuwzho","name":"PhotoAlbum-Java"}}